pan_baidu_sdk/__init__.py
pan_baidu_sdk/auth.py
pan_baidu_sdk/download.py
pan_baidu_sdk/file.py
pan_baidu_sdk/main.py
pan_baidu_sdk/upload.py
pan_baidu_sdk/user.py
pan_baidu_sdk/utils.py
pan_baidu_sdk-0.1.2.dist-info/METADATA
pan_baidu_sdk-0.1.2.dist-info/WHEEL
pan_baidu_sdk-0.1.2.dist-info/RECORD
