Metadata-Version: 2.4
Name: pan-baidu-sdk
Version: 0.1.2
Summary: 百度网盘 SDK，提供文件上传、下载、列表等功能的 Python 接口
Author-email: Your Name <your.email@example.com>
License: MIT
Classifier: License :: OSI Approved :: MIT License
Classifier: Operating System :: OS Independent
Classifier: Programming Language :: Python :: 3
Requires-Python: >=3.12
Requires-Dist: baidu-openapi-client>=0.1.0
Requires-Dist: requests>=2.32.3
